mycal/cal.py
EKONG45223688-0.0.1.dist-info/METADATA
EKONG45223688-0.0.1.dist-info/WHEEL
EKONG45223688-0.0.1.dist-info/top_level.txt
EKONG45223688-0.0.1.dist-info/RECORD
