Metadata-Version: 2.1
Name: EKONG45223688
Version: 0.0.1
Summary: cal0001
Home-page: https://github.com/EE-KONG/MyCalculator001
Download-URL: https://github.com/EE-KONG/MyCalculator001/archive/refs/v0.0.1.zip
Author: kimsm
Author-email: mahaha0309@gmail.com
License: UNKNOWN
Platform: UNKNOWN
Classifier: Programming Language :: Python :: 3
Classifier: Operating System :: OS Independent
